chonker/__init__.py
chonker/compute.py
chonker/wrangle.py
chonker/chonktorch/__init__.py
chonker/chonktorch/data.py
chonker/chonktorch/data_classes.py
chonker/chonktorch/functions.py
chonker-1.4.3.dist-info/LICENSE.txt
chonker-1.4.3.dist-info/METADATA
chonker-1.4.3.dist-info/WHEEL
chonker-1.4.3.dist-info/top_level.txt
chonker-1.4.3.dist-info/RECORD
