Metadata-Version: 2.1
Name: chonker
Version: 1.4.3
Summary: A utility package for NLP and Machine Learning
Home-page: https://github.com/cmdowney88/chonker
Author: C.M. Downey
Author-email: cmdowney@uw.edu
License: UNKNOWN
Platform: UNKNOWN
Classifier: Programming Language :: Python :: 3
Classifier: License :: OSI Approved :: Mozilla Public License 2.0 (MPL 2.0)
Classifier: Operating System :: OS Independent
Requires-Python: >=3.5
Requires-Dist: numpy
Requires-Dist: pyyaml
Requires-Dist: torch
